{"id":"134_003_chunked_merge_based_schema_inference_01_audit","status":"rejected","attempt":0,"ts":"2026-07-18T12:09:03.455577Z","repair_report":"Tests failed (2 failed, 0 errors):\n  - test an empty fragment has nil names, zero ncols and no categories (MergeSchemaTest): \n\nAssertion with == failed\ncode:  assert empty.names == nil\nleft:  []\nright: nil\n\n  - test an empty fragment is a neutral element for merge in both orders (MergeSchemaTest): \n\nAssertion with == failed\ncode:  assert MergeSchema.finalize(MergeSchema.merge(empty, p)) == expected\nleft:  %{}\nright: %{\"m\" => :float, \"n\" => :integer}\n"}